pyquil/__init__.py
pyquil/_version.py
pyquil/api/__init__.py
pyquil/api/_abstract_compiler.py
pyquil/api/_benchmark.py
pyquil/api/_compiler.py
pyquil/api/_compiler_client.py
pyquil/api/_logger.py
pyquil/api/_qam.py
pyquil/api/_qpu.py
pyquil/api/_quantum_computer.py
pyquil/api/_qvm.py
pyquil/api/_wavefunction_simulator.py
pyquil/control_flow_graph.py
pyquil/diagnostics.py
pyquil/experiment/__init__.py
pyquil/experiment/_calibration.py
pyquil/experiment/_group.py
pyquil/experiment/_main.py
pyquil/experiment/_memory.py
pyquil/experiment/_program.py
pyquil/experiment/_result.py
pyquil/experiment/_setting.py
pyquil/experiment/_symmetrization.py
pyquil/external/README.md
pyquil/external/__init__.py
pyquil/external/rpcq.py
pyquil/gates.py
pyquil/latex/__init__.py
pyquil/latex/_diagram.py
pyquil/latex/_ipython.py
pyquil/latex/_main.py
pyquil/latex/latex_generation.py
pyquil/noise.py
pyquil/noise_gates.py
pyquil/operator_estimation.py
pyquil/paulis.py
pyquil/py.typed
pyquil/pyqvm.py
pyquil/quantum_processor/__init__.py
pyquil/quantum_processor/_base.py
pyquil/quantum_processor/_isa.py
pyquil/quantum_processor/compiler.py
pyquil/quantum_processor/graph.py
pyquil/quantum_processor/qcs.py
pyquil/quantum_processor/transformers/__init__.py
pyquil/quantum_processor/transformers/compiler_isa_to_graph.py
pyquil/quantum_processor/transformers/graph_to_compiler_isa.py
pyquil/quantum_processor/transformers/qcs_isa_to_compiler_isa.py
pyquil/quantum_processor/transformers/qcs_isa_to_graph.py
pyquil/quil.py
pyquil/quilatom.py
pyquil/quilbase.py
pyquil/quiltcalibrations.py
pyquil/quiltwaveforms.py
pyquil/simulation/__init__.py
pyquil/simulation/_numpy.py
pyquil/simulation/_reference.py
pyquil/simulation/matrices.py
pyquil/simulation/tools.py
pyquil/wavefunction.py
pyquil_grpc_web-4.14.2.dist-info/LICENSE
pyquil_grpc_web-4.14.2.dist-info/METADATA
pyquil_grpc_web-4.14.2.dist-info/NOTICE.md
pyquil_grpc_web-4.14.2.dist-info/WHEEL
pyquil_grpc_web-4.14.2.dist-info/RECORD
