Metadata-Version: 2.1
Name: pyquil-grpc-web
Version: 4.14.2
Summary: A Python library for creating Quantum Instruction Language (Quil) programs.
Home-page: https://github.com/rigetti/pyquil.git
License: Apache-2.0
Keywords: quantum,quil,programming,hybrid
Author: Rigetti Computing
Author-email: softapps@rigetti.com
Requires-Python: >=3.9,<4.0
Classifier: Development Status :: 5 - Production/Stable
Classifier: License :: OSI Approved :: Apache Software License
Classifier: Operating System :: OS Independent
Classifier: Programming Language :: Python :: 3
Classifier: Programming Language :: Python :: 3.9
Classifier: Programming Language :: Python :: 3.10
Classifier: Programming Language :: Python :: 3.11
Classifier: Programming Language :: Python :: 3.12
Classifier: Programming Language :: Python :: 3.8
Provides-Extra: docs
Provides-Extra: latex
Requires-Dist: Sphinx (>=7.3.7,<8.0.0) ; extra == "docs"
Requires-Dist: deprecated (>=1.2.14,<2.0.0)
Requires-Dist: ipython (>=8.16.0,<9.0.0) ; extra == "latex"
Requires-Dist: matplotlib (>=3.9.0,<4.0.0) ; extra == "docs"
Requires-Dist: matplotlib-inline (>=0.1.7,<0.2.0)
Requires-Dist: myst-parser (>=3.0.1,<4.0.0) ; extra == "docs"
Requires-Dist: nbsphinx (>=0.9.3,<0.10.0) ; extra == "docs"
Requires-Dist: networkx (>=2.5)
Requires-Dist: numpy (>=1.25,<2.0)
Requires-Dist: packaging (>=23.1,<24.0)
Requires-Dist: pandoc (==2.4b0) ; extra == "docs"
Requires-Dist: qcs-sdk-python-grpc-web (>=0.19.2)
Requires-Dist: quil (>=0.11.2)
Requires-Dist: rpcq (>=3.11.0,<4.0.0)
Requires-Dist: scipy (>=1.11,<2.0)
Requires-Dist: seaborn (>=0.13.2,<0.14.0) ; extra == "docs"
Requires-Dist: sphinx-rtd-theme (>=1.3.0,<2.0.0) ; extra == "docs"
Requires-Dist: types-deprecated (>=1.2.9.3,<2.0.0.0)
Project-URL: Documentation, https://pyquil-docs.rigetti.com
Project-URL: Repository, https://github.com/rigetti/pyquil.git
